docs/__init__.py
docs/authenticator.py
docs/blockchain.py
docs/digital_signature.py
docs/encode_decode.py
docs/node.py
docs/qkd.py
docs/tallier.py
docs/voter.py
quantumvoting/__init__.py
quantumvoting/authenticator.py
quantumvoting/blockchain.py
quantumvoting/digital_signature.py
quantumvoting/encode_decode.py
quantumvoting/node.py
quantumvoting/qkd.py
quantumvoting/tallier.py
quantumvoting/voter.py
sawty-0.1.1.dist-info/LICENSE.md
sawty-0.1.1.dist-info/METADATA
sawty-0.1.1.dist-info/WHEEL
sawty-0.1.1.dist-info/top_level.txt
sawty-0.1.1.dist-info/RECORD
