Metadata-Version: 2.1
Name: sawty
Version: 0.1.1
Summary: Quantum-Secure Voting System
Home-page: https://github.com/AdrianHarkness/NYUAD2025
Author: NYUAD 2025 Team 6 SAWTY
Classifier: Programming Language :: Python :: 3
Classifier: License :: OSI Approved :: MIT License
Classifier: Operating System :: OS Independent
Requires-Python: >=3.8
License-File: LICENSE.md
Requires-Dist: qiskit
Requires-Dist: cryptography
